README.md
setup.py
common/__init__.py
common/decos.py
common/descryptors.py
common/errors.py
common/metaclasses.py
common/utils.py
common/variables.py
gb_training_client.egg-info/PKG-INFO
gb_training_client.egg-info/SOURCES.txt
gb_training_client.egg-info/dependency_links.txt
gb_training_client.egg-info/requires.txt
gb_training_client.egg-info/top_level.txt
logs/__init__.py
logs/config_client_log.py
logs/config_server_log.py