Metadata-Version: 1.0
Name: gb-training-client
Version: 0.0.1
Summary: mess_client
Home-page: UNKNOWN
Author: Ruslan Akmanov
Author-email: UNKNOWN
License: UNKNOWN
Platform: UNKNOWN
